agents_mcp/__init__.py
agents_mcp/agent.py
agents_mcp/agent_hooks.py
agents_mcp/aggregator.py
agents_mcp/context.py
agents_mcp/logger.py
agents_mcp/server_registry.py
agents_mcp/tools.py
openai_agents_mcp-0.0.7.dist-info/METADATA
openai_agents_mcp-0.0.7.dist-info/WHEEL
openai_agents_mcp-0.0.7.dist-info/licenses/LICENSE
openai_agents_mcp-0.0.7.dist-info/RECORD
