Metadata-Version: 2.4
Name: openai-agents-mcp
Version: 0.0.7
Summary: MCP (Model Context Protocol) extension for OpenAI Agents SDK, built using mcp-agent
Project-URL: Homepage, https://github.com/saqadri/openai-agents-mcp
Project-URL: Repository, https://github.com/saqadri/openai-agents-mcp
Author-email: Sarmad Qadri <sarmad@lastmileai.dev>
License-Expression: MIT
License-File: LICENSE
Classifier: Intended Audience :: Developers
Classifier: License :: OSI Approved :: MIT License
Classifier: Operating System :: OS Independent
Classifier: Programming Language :: Python :: 3
Classifier: Programming Language :: Python :: 3.10
Classifier: Programming Language :: Python :: 3.11
Classifier: Programming Language :: Python :: 3.12
Classifier: Topic :: Software Development :: Libraries :: Python Modules
Classifier: Typing :: Typed
Requires-Python: >=3.10
Requires-Dist: mcp-agent>=0.0.9
Requires-Dist: openai-agents>=0.0.5
